.DS_Store
doctext/Capabilities.py
doctext/Processor.py
doctext/__init__.py
doctext/textextract.py
doctext/utils.py
doctext-0.2.0.dist-info/LICENSE
doctext-0.2.0.dist-info/METADATA
doctext-0.2.0.dist-info/WHEEL
doctext-0.2.0.dist-info/top_level.txt
doctext-0.2.0.dist-info/RECORD
