Metadata-Version: 2.1
Name: doctext
Version: 0.2.0
Home-page: https://github.com/luckfamousa/doctext
Author: Felix Nensa
Author-email: felix.nensa@gmail.com
License: MIT
License-File: LICENSE
Requires-Dist: docling
Requires-Dist: tika
Requires-Dist: Pillow
Requires-Dist: pytesseract
Requires-Dist: termcolor
Requires-Dist: python-magic
Requires-Dist: openai
Requires-Dist: chardet
Requires-Dist: langdetect
Requires-Dist: iso639-lang
Requires-Dist: pdfminer.six
